TESTBENCH/simulation_modules.v
/* Modul symulacyjny do
    - generacji sygnalow globalnych RST i CLK
    - zapisywania wynikow symulacji 
    - konczenia symulacji po liczbie cykli 
*/
module global_signals 
    #(
        parameter SIM_CLOCK_CYCLES  = 120,
        parameter CLOCK_PERIOD      = 10,
        parameter SIGNAL_VCD_FILE   = "SIGNALS.vcd"
    )
    (
        output wire o_CLK,
        output wire o_RSTn
    );
        
        reg clk;
        reg rst_n;

        assign o_CLK = clk;
        assign o_RSTn = rst_n;

        localparam CLK_PERIOD = CLOCK_PERIOD;
        always #(CLK_PERIOD/2) 
            clk=~clk;

        initial begin
            $dumpfile(SIGNAL_VCD_FILE);
            $dumpvars(0, testbench);
        end

        initial begin
            #1;
            rst_n<=1'bx; clk<=1'bx;
            
            #(CLK_PERIOD*3) rst_n<=1;
            
            #(CLK_PERIOD*3) rst_n<=0;clk<=0;
            
            repeat(5) 
                @(posedge clk);
            
            rst_n<=1;
            @(posedge clk);

            repeat(SIM_CLOCK_CYCLES) 
                @(posedge clk);

            $finish;
        end
endmodule

/*
    Modul generacji losowych wartosci sygnalu wielobitowego -- sterowanie protokolem READY-VALID
*/
module random_vector
    #(
        parameter WIDTH = 9
    ) 
    (
        input  wire i_CLK,
        input  wire i_RSTn,
        input  wire i_READY,
        output wire o_VALID,
        output wire [WIDTH-1 : 0] o_Y
    );
        integer             SEED = 100;
        reg                 s_was_valid;
        reg [WIDTH-1 : 0]   s_Y;
        reg                 s_VALID;

        assign #(1) o_Y     = s_Y;
        assign #(1) o_VALID = s_VALID;

        initial 
        begin
            #1;
            @(posedge i_RSTn);

            s_Y         <= {WIDTH{1'b0}};
            s_VALID     <= 1'b0;
            s_was_valid <= 1'b0;

            forever 
            begin
                fork 
                    begin : GENEROWANIE_SYGNALOW_WYJSCIOWYCH
                        @(posedge i_CLK)
                        begin
                            s_VALID <= $random(SEED);
                            if (i_READY == 1'b1 && s_was_valid == 1'b1)
                                {s_Y} <= {s_Y, $random(SEED)};
                        end
                        
                        if (i_RSTn == 1'b0)
                            @(posedge i_RSTn);
                    end

                    begin : ZAPAMIETANIE_POPRZEDNIEGO_VALID
                        @(negedge i_CLK)
                            s_was_valid <= s_VALID;
                    end
                join
            end
        end
endmodule


/*
    Modul odbioru wartosci sygnalu wielobitowego -- sterowanie protokolem READY-VALID
*/
module vector_data_accept 
#(
    parameter WIDTH = 8
)
(
        input  wire               i_CLK,
        input  wire               i_RSTn,
        input  wire               i_VALID,
        input  wire [WIDTH-1 : 0] i_D,
        output wire               o_READY
);

    integer SEED = 100;
    reg [WIDTH-1 : 0]   s_DATA;
    reg s_READY;

    assign #(1) o_READY = s_READY;

    initial 
    begin
        #1;
        @(posedge i_RSTn);

        s_READY     <= 1'b0;

        forever 
        begin
            @(posedge i_CLK)
            begin
                if (s_READY == 1'b1 && i_VALID == 1'b1) 
                        s_DATA <= i_D;
                s_READY <= $random(SEED);
            end
            
            if (i_RSTn == 1'b0)
            begin
                s_READY <= 1'b0;
                @(posedge i_RSTn);
            end

        end
    end

endmodule

MODEL/library_modules.v
// Y = A - B czyli odejmowacz
module subtractor #(
    parameter WIDTH = 4
)
(
    input wire signed [WIDTH-1:0] i_a,
    input wire signed [WIDTH-1:0] i_b,
    output reg signed [WIDTH-1:0] o_y,
    output reg                    o_overflow,
    output reg                    o_err             // nie dotyczy
);
    always @(*) begin
        o_y = i_a - i_b;
        // overflow bedzie widac gdy przy przeciwnych znakach A, B Y bedzie miala znak przeciwny do A
        o_overflow = (i_a[WIDTH-1] != i_b[WIDTH-1]) && (i_a[WIDTH-1] != o_y[WIDTH-1]);
        o_err = 1'b0;
    end
endmodule

// Y = A nand B czyli nandownik :)
module nand_gate #(
    parameter WIDTH = 4
)
(
    input wire signed [WIDTH-1:0] i_a,
    input wire signed [WIDTH-1:0] i_b,
    output reg signed [WIDTH-1:0] o_y,
    output reg                    o_overflow,   // nie dotyczy
    output reg                    o_err         // nie dotyczy
);
    always @(*) begin
        o_y = ~(i_a & i_b);                 // NAND = ~AND
        o_overflow = 1'b0;
        o_err = 1'b0;
    end
endmodule

// liczba wiodacych jedynek wektora {B,A} liczac od MSB, czyli wiodacy
module starting_ones #(
    parameter WIDTH = 4
)
(
    input wire signed [WIDTH-1:0] i_a,
    input wire signed [WIDTH-1:0] i_b,
    output reg        [WIDTH-1:0] o_y,
    output reg                    o_overflow, 
    output reg                    o_err             // nie dotyczy
);
    reg [WIDTH+WIDTH-1:0] c;
    integer i;
    integer count;

    always @(*) begin
        // polaczenie wektorow
        c = {i_b, i_a};
        count = 0;
    // sprawdz od MSB ile jest 1, a jesli pojawi sie 0 to przerwij fora = przestan liczyc
        for (i = WIDTH+WIDTH-1; i >= 0; i = i-1)
            if (c[i] == 1)
                count = count + 1;

        // ustaw overflow 1, jesli wiodących jedynek będzie więcej niż maksymanla warosc o_y (na razie WIDTH)
        o_overflow = (count > (2**WIDTH-1)) ? 1'b1 : 1'b0;
        o_err = 1'b0;
        o_y = count[WIDTH-1:0];
    end
endmodule

// onehot do u2 (a w zasadzie do nkb, bo nie moze byc ujemnych), czyli dekoder
module onehot2u2_decoder #(
    parameter LEN = 8,
    // WIDTH musi wynosic tyle co log2(LEN+LEN)
    parameter WIDTH = 4
)
(
    input wire [LEN-1:0] i_a_oh,
    input wire [LEN-1:0] i_b_oh,
    output reg [WIDTH-1:0] o_y_u2,
    output reg             o_overflow,
    output reg             o_err
);
    reg s_was1;
    integer i;
    integer posit;
    reg [LEN+LEN-1:0] i_onehot;
    always @(*) begin
        // wyzeruj wartosci 
        o_y_u2 = 0;
        o_overflow = 1'b0;
        o_err   = 1'b0;
        s_was1  = 1'b0;
        posit     = 0;
        // polacz B, A
        i_onehot = {i_b_oh, i_a_oh};

        for (i=0; i < (LEN+LEN); i = i+1)
            if (i_onehot[i] == 1'b1)
                if (s_was1)
                    o_err = 1'b1;           // wyswietl blad jesli to kolejna jedynka
                else
                begin
                    s_was1 = 1'b1;
                    posit = i;             // ustaw pamiec o tym, ze jedynka juz byla i przechowaj wartosc z oh
                end
        o_overflow = (posit > (2**WIDTH-1)) ? 1'b1 : 1'b0;
        o_y_u2 = posit[WIDTH-1:0];
    end
endmodule

MODEL/top.v
module TOP #(
    parameter WIDTH = 4,
    parameter LEN = 2
)
(
    input wire [WIDTH-1 : 0]    i_arg0,
    input wire [WIDTH-1 : 0]    i_arg1,
    input wire                  i_oper,
    input wire                  i_clk,
    input wire                  i_rstn,
    output reg [3:0]            o_flag,
    output reg [WIDTH-1 : 0]    o_result
);

    wire [WIDTH-1:0] sub_result, nand_result, oh_result, decoder_result;
    wire sub_overflow, sub_err;
    wire nand_overflow, nand_err;
    wire oh_overflow, oh_err;
    wire decoder_overflow, decoder_err;

    
    subtractor #(.WIDTH(WIDTH))
    u_subtractor
    (
        .i_a(i_arg0),
        .i_b(i_arg1),
        .o_y(sub_result),
        .o_overflow(sub_overflow),
        .o_err(sub_err)
    );
    nand_gate #(.WIDTH(WIDTH))
    u_nand_gate
    (
        .i_a(i_arg0),
        .i_b(i_arg1),
        .o_y(nand_result),
        .o_overflow(nand_overflow),
        .o_err(nand_err)
    );
    starting_ones #(.WIDTH(WIDTH))
    u_starting_ones
    (
        .i_a(i_arg0),
        .i_b(i_arg1),
        .o_y(oh_result),
        .o_overflow(oh_overflow),
        .o_err(oh_err)
    );
    onehot2u2_decoder #(.LEN(LEN), .WIDTH(WIDTH))
    u_decoder
    (
        .i_a_oh(i_arg0),
        .i_b_oh(i_arg1),
        .o_y_u2(decoder_result),
        .o_overflow(decoder_overflow),
        .o_err(decoder_err)
    );

    // sygnaly temp do flag
    reg temp_overflow, temp_err, temp_neg, temp_pos;

    always @(*) begin
        o_result = 0;
        temp_overflow = 0;
        temp_err = 0;
        temp_neg = 0;
        temp_pos = 0;
        case(i_oper)
            2'b00: begin
                o_result = sub_result;
                temp_overflow = sub_overflow;
                temp_err = sub_err;
            end
            2'b01: begin
                o_result = nand_result;
                temp_overflow = nand_overflow;
                temp_err = nand_err;                
            end
            2'b10: begin
                o_result = oh_result;
                temp_overflow = oh_overflow;
                temp_err = oh_err;                                
            end
            2'b11: begin
                o_result = decoder_result;
                temp_overflow = decoder_overflow;
                temp_err = decoder_err;                                
            end
        endcase
    temp_pos = ~o_result[WIDTH-1] & (o_result != 0);
    temp_neg = o_result[WIDTH-1] & (o_result != 0);

    // wszystkie flagi na jednym wyjsciu
    o_flag[0] = temp_err;
    o_flag[1] = temp_neg;
    o_flag[2] = temp_pos;
    o_flag[3] = temp_overflow;
    end
endmodule

TESTBENCH/testbench.v
// Glowny modul symulacji -- musi nazywac sie testbench ze wzgledu na skrypty symulacyjne
module testbench;

    localparam DATA_WIDTH = 4;

    reg [DATA_WIDTH-1:0] s_A, s_B;
    wire [DATA_WIDTH-1:0] s_Y;
    reg [1:0] s_sel;
    wire s_CLK;
    wire s_RSTn;
    
    wire [3:0] s_flag;  
    
    // pozycje sygnalu _flag
    localparam FLAG_ERR      = 0;
    localparam FLAG_NEG      = 1;
    localparam FLAG_POS      = 2;
    localparam FLAG_OVERFLOW = 3; 

    // Modul nadrzedny hierarchii projektu
    TOP #(.WIDTH(DATA_WIDTH), .LEN(2))   // Nazwa modulu -- MUSI BYC TOP ze wzgledu na skrypty symulacyjne i syntezy
        UTOP                    // Nazwa instancji -- MUSI BYC UTOP ze wzgledu na skrypty syntezy logicznej i symulacji
            (
                .i_arg0(s_A),
                .i_arg1(s_B),
                .i_oper(s_sel),
                .i_clk(s_CLK),
                .i_rstn(s_RSTn),
                .o_result(s_Y),
                .o_flag(s_flag)
            );

    //
    // Komponenty symulacyjne
    //
    integer i;
    initial begin
        s_A = 0;
        s_B = 0;
        s_sel = 0;

        //reset
        @(posedge s_RSTn);;
        @(posedge s_CLK);

        // test wszystkich kombinacji
        for (i = 0; i < 50; i = i+1) begin
            @(posedge s_CLK);
            s_A = $random;
            s_B = $random;
            s_sel = $random;
        end
        
        // test na konkretnych wartościach
        @(posedge s_CLK);
        s_A = 4'b0101;
        s_B = 4'b0011;
        s_sel = 2'b00;  // substractor

        @(posedge s_CLK);
        s_A = 4'b1111;
        s_B = 4'b0000;
        s_sel = 2'b01;  // nand

        @(posedge s_CLK);
        s_A = 4'b1100;
        s_B = 4'b0011;
        s_sel = 2'b10;  // starting_ones

        @(posedge s_CLK);
        s_A = 4'b0010;
        s_B = 4'b1000;
        s_sel = 2'b11;  // onehot2u2_decoder
    end
    
    // Generator globalnych sygnalow CLK i RST oraz zakonczenia symulacji
    global_signals #(.SIM_CLOCK_CYCLES(100), .CLOCK_PERIOD(10))
        U_RST_CLK
            (.o_CLK(s_CLK), .o_RSTn(s_RSTn));


endmodule

SIGNALS.vcd
$date
	Sun Dec 21 19:55:15 2025
$end
$version
	Icarus Verilog
$end
$timescale
	1s
$end
$scope module testbench $end
$var wire 4 ! s_flag [3:0] $end
$var wire 4 " s_Y [3:0] $end
$var wire 1 # s_RSTn $end
$var wire 1 $ s_CLK $end
$var parameter 32 % DATA_WIDTH $end
$var parameter 32 & FLAG_ERR $end
$var parameter 32 ' FLAG_NEG $end
$var parameter 32 ( FLAG_OVERFLOW $end
$var parameter 32 ) FLAG_POS $end
$var reg 4 * s_A [3:0] $end
$var reg 4 + s_B [3:0] $end
$var reg 2 , s_sel [1:0] $end
$var integer 32 - i [31:0] $end
$scope module UTOP $end
$var wire 4 . i_arg0 [3:0] $end
$var wire 4 / i_arg1 [3:0] $end
$var wire 1 0 i_oper $end
$var wire 4 1 sub_result [3:0] $end
$var wire 1 2 sub_overflow $end
$var wire 1 3 sub_err $end
$var wire 4 4 oh_result [3:0] $end
$var wire 1 5 oh_overflow $end
$var wire 1 6 oh_err $end
$var wire 4 7 nand_result [3:0] $end
$var wire 1 8 nand_overflow $end
$var wire 1 9 nand_err $end
$var wire 1 # i_rstn $end
$var wire 1 $ i_clk $end
$var wire 4 : decoder_result [3:0] $end
$var wire 1 ; decoder_overflow $end
$var wire 1 < decoder_err $end
$var parameter 32 = LEN $end
$var parameter 32 > WIDTH $end
$var reg 4 ? o_flag [3:0] $end
$var reg 4 @ o_result [3:0] $end
$var reg 1 A temp_err $end
$var reg 1 B temp_neg $end
$var reg 1 C temp_overflow $end
$var reg 1 D temp_pos $end
$scope module u_decoder $end
$var wire 2 E i_a_oh [1:0] $end
$var wire 2 F i_b_oh [1:0] $end
$var parameter 32 G LEN $end
$var parameter 32 H WIDTH $end
$var reg 4 I i_onehot [3:0] $end
$var reg 1 < o_err $end
$var reg 1 ; o_overflow $end
$var reg 4 J o_y_u2 [3:0] $end
$var reg 1 K s_was1 $end
$var integer 32 L i [31:0] $end
$var integer 32 M posit [31:0] $end
$upscope $end
$scope module u_nand_gate $end
$var wire 4 N i_a [3:0] $end
$var wire 4 O i_b [3:0] $end
$var parameter 32 P WIDTH $end
$var reg 1 9 o_err $end
$var reg 1 8 o_overflow $end
$var reg 4 Q o_y [3:0] $end
$upscope $end
$scope module u_starting_ones $end
$var wire 4 R i_a [3:0] $end
$var wire 4 S i_b [3:0] $end
$var parameter 32 T WIDTH $end
$var reg 8 U c [7:0] $end
$var reg 1 6 o_err $end
$var reg 1 5 o_overflow $end
$var reg 4 V o_y [3:0] $end
$var integer 32 W count [31:0] $end
$var integer 32 X i [31:0] $end
$upscope $end
$scope module u_subtractor $end
$var wire 4 Y i_a [3:0] $end
$var wire 4 Z i_b [3:0] $end
$var parameter 32 [ WIDTH $end
$var reg 1 3 o_err $end
$var reg 1 2 o_overflow $end
$var reg 4 \ o_y [3:0] $end
$upscope $end
$upscope $end
$scope module U_RST_CLK $end
$var wire 1 $ o_CLK $end
$var wire 1 # o_RSTn $end
$var parameter 32 ] CLK_PERIOD $end
$var parameter 32 ^ CLOCK_PERIOD $end
$var parameter 88 _ SIGNAL_VCD_FILE $end
$var parameter 32 ` SIM_CLOCK_CYCLES $end
$var reg 1 a clk $end
$var reg 1 b rst_n $end
$upscope $end
$upscope $end
$enddefinitions $end
$comment Show the parameter values. $end
$dumpall
b1100100 `
b101001101001001010001110100111001000001010011000101001100101110011101100110001101100100 _
b1010 ^
b1010 ]
b100 [
b100 T
b100 P
b100 H
b10 G
b100 >
b10 =
b10 )
b11 (
b1 '
b0 &
b100 %
$end
#0
$dumpvars
xb
xa
b0 \
b0 Z
b0 Y
b11111111111111111111111111111111 X
b0 W
b0 V
b0 U
b0 S
b0 R
b1111 Q
b0 O
b0 N
b0 M
b100 L
0K
b0 J
b0 I
b0 F
b0 E
0D
0C
0B
0A
b0 @
b0 ?
0<
0;
b0 :
09
08
b1111 7
06
05
b0 4
03
02
b0 1
00
b0 /
b0 .
bx -
b0 ,
b0 +
b0 *
x$
x#
b0 "
b0 !
$end
#31
1#
1b
#61
0$
0a
0#
0b
#65
b0 -
1$
1a
#70
0$
0a
#75
b10 :
b10 J
b10 M
1K
b100 L
b100 I
b10 !
b10 ?
1B
b1111 "
b1111 @
10
b1 F
b10 4
b10 V
b10 W
b11111111111111111111111111111111 X
b10100 U
b11 1
b11 \
b1 -
b1 ,
b1 +
b1 /
b1 O
b1 S
b1 Z
b100 *
b100 .
b100 N
b100 R
b100 Y
1$
1a
#80
0$
0a
#85
1<
b100 L
b111 I
b0 M
1K
b0 :
b0 J
1B
b1110 "
b1110 @
b11 E
b1110 7
b1110 Q
b101 4
b101 V
b11111111111111111111111111111111 X
b101 W
b11010011 U
b110 1
b110 \
b10 -
b1101 +
b1101 /
b1101 O
b1101 S
b1101 Z
b11 *
b11 .
b11 N
b11 R
b11 Y
1$
1a
#90
0$
0a
#95
b100 L
b1001 I
1K
1<
1B
b1111 "
b1111 @
b10 F
b1 E
b1111 7
b1111 Q
b11 4
b11 V
b11111111111111111111111111111111 X
b11 W
b100101 U
b11 1
b11 \
b11 -
b10 +
b10 /
b10 O
b10 S
b10 Z
b101 *
b101 .
b101 N
b101 R
b101 Y
1$
1a
#100
0$
0a
#105
1#
1b
1B
b1011 "
b1011 @
b1011 7
b1011 Q
b101 4
b101 V
b11111111111111111111111111111111 X
b101 W
b1101101 U
12
b111 1
b111 \
b100 -
b110 +
b110 /
b110 O
b110 S
b110 Z
b1101 *
b1101 .
b1101 N
b1101 R
b1101 Y
1$
1a
#110
0$
0a
#115
b100 L
b1 I
1K
0<
b100 !
b100 ?
1D
0B
b11 "
b11 @
b0 F
b11 7
b11 Q
b11111111111111111111111111111111 X
b101 W
b11001101 U
02
b1 1
b1 \
b101 -
b1100 +
b1100 /
b1100 O
b1100 S
b1100 Z
1$
1a
#120
0$
0a
#125
b1 :
b1 J
1<
b1 M
b100 L
b110 I
1K
1D
b1 "
b1 @
00
b1 F
b10 E
b1011 7
b1011 Q
b100 4
b100 V
b11111111111111111111111111111111 X
b100 W
b1010110 U
b110 -
b10 ,
b101 +
b101 /
b101 O
b101 S
b101 Z
b110 *
b110 .
b110 N
b110 R
b110 Y
1$
1a
#130
0$
0a
#135
b100 L
b1101 I
b0 M
1K
1<
b0 :
b0 J
b10 !
b10 ?
1B
0D
b1110 "
b1110 @
b11 F
b1 E
b1010 7
b1010 Q
b101 4
b101 V
b11111111111111111111111111111111 X
b101 W
b1110101 U
b1110 1
b1110 \
b111 -
b111 +
b111 /
b111 O
b111 S
b111 Z
b101 *
b101 .
b101 N
b101 R
b101 Y
1$
1a
#140
0$
0a
#145
b100 L
b1011 I
1K
1<
1B
b1101 "
b1101 @
b10 F
b11 E
b1101 7
b1101 Q
b11111111111111111111111111111111 X
b101 W
b101111 U
b1101 1
b1101 \
b1000 -
b10 +
b10 /
b10 O
b10 S
b10 Z
b1111 *
b1111 .
b1111 N
b1111 R
b1111 Y
1$
1a
#150
0$
0a
#155
b10 :
b10 J
b10 M
b100 L
b100 I
1K
0<
b1100 !
b1100 ?
1D
1C
0B
b11 "
b11 @
b1 F
b0 E
b1111 7
b1111 Q
b11 4
b11 V
b11111111111111111111111111111111 X
b11 W
b1011000 U
12
b11 1
b11 \
b1001 -
b0 ,
b101 +
b101 /
b101 O
b101 S
b101 Z
b1000 *
b1000 .
b1000 N
b1000 R
b1000 Y
1$
1a
#160
0$
0a
#165
1<
b100 L
b101 I
b0 M
1K
b0 :
b0 J
b100 !
b100 ?
1D
0C
b10 "
b10 @
10
b1 E
b10 7
b10 Q
b110 4
b110 V
b11111111111111111111111111111111 X
b110 W
b11011101 U
02
b0 1
b0 \
b1010 -
b1 ,
b1101 +
b1101 /
b1101 O
b1101 S
b1101 Z
b1101 *
b1101 .
b1101 N
b1101 R
b1101 Y
1$
1a
#170
0$
0a
#175
b100 L
b1011 I
1K
1<
b1010 !
b1010 ?
1B
1C
0D
b1001 "
b1001 @
00
b10 F
b11 E
b1101 7
b1101 Q
b100 4
b100 V
b11111111111111111111111111111111 X
b100 W
b10100011 U
12
b1001 1
b1001 \
b1011 -
b0 ,
b1010 +
b1010 /
b1010 O
b1010 S
b1010 Z
b11 *
b11 .
b11 N
b11 R
b11 Y
1$
1a
#180
0$
0a
#185
b11 :
b11 J
b11 M
b100 L
b1000 I
1K
0<
b10 !
b10 ?
1B
0C
b1111 "
b1111 @
10
b0 E
b1111 7
b1111 Q
b10 4
b10 V
b11111111111111111111111111111111 X
b10 W
b10100000 U
02
b110 1
b110 \
b1100 -
b1 ,
b0 *
b0 .
b0 N
b0 R
b0 Y
1$
1a
#190
0$
0a
#195
1<
b100 L
b1110 I
b1 M
1K
b1 :
b1 J
1B
b1101 "
b1101 @
b11 F
b10 E
b1101 7
b1101 Q
b100 4
b100 V
b11111111111111111111111111111111 X
b100 W
b110110 U
b11 1
b11 \
b1101 -
b11 +
b11 /
b11 O
b11 S
b11 Z
b110 *
b110 .
b110 N
b110 R
b110 Y
1$
1a
#200
0$
0a
#205
b100 L
b1111 I
b0 M
1K
1<
b0 :
b0 J
1B
b1100 "
b1100 @
b11 E
b1100 7
b1100 Q
b101 4
b101 V
b11111111111111111111111111111111 X
b101 W
b10110011 U
12
b1000 1
b1000 \
b1110 -
b1011 +
b1011 /
b1011 O
b1011 S
b1011 Z
b11 *
b11 .
b11 N
b11 R
b11 Y
1$
1a
#210
0$
0a
#215
b1 :
b1 J
b1 M
b100 L
b1010 I
1K
1<
1B
b1101 "
b1101 @
b10 F
b10 E
b1101 7
b1101 Q
b100 4
b100 V
b11111111111111111111111111111111 X
b100 W
b11100010 U
02
b100 1
b100 \
b1111 -
b1110 +
b1110 /
b1110 O
b1110 S
b1110 Z
b10 *
b10 .
b10 N
b10 R
b10 Y
1$
1a
#220
0$
0a
#225
b100 L
b1111 I
b0 M
1K
1<
b0 :
b0 J
1B
b1100 "
b1100 @
00
b11 F
b11 E
b1100 7
b1100 Q
b110 4
b110 V
b11111111111111111111111111111111 X
b110 W
b111111 U
b1100 1
b1100 \
b10000 -
b10 ,
b11 +
b11 /
b11 O
b11 S
b11 Z
b1111 *
b1111 .
b1111 N
b1111 R
b1111 Y
1$
1a
#230
0$
0a
#235
b1 :
b1 J
b1 M
b100 L
b10 I
1K
0<
1B
b1110 "
b1110 @
b0 F
b10 E
b111 7
b111 Q
b100 4
b100 V
b11111111111111111111111111111111 X
b100 W
b11001010 U
b1110 1
b1110 \
b10001 -
b1100 +
b1100 /
b1100 O
b1100 S
b1100 Z
b1010 *
b1010 .
b1010 N
b1010 R
b1010 Y
1$
1a
#240
0$
0a
#245
1<
b100 L
b110 I
b1 M
1K
b1 :
b1 J
1B
b1001 "
b1001 @
b1 F
b1111 7
b1111 Q
b11 4
b11 V
b11111111111111111111111111111111 X
b11 W
b11010 U
b1001 1
b1001 \
b10010 -
b0 ,
b1 +
b1 /
b1 O
b1 S
b1 Z
1$
1a
#250
0$
0a
#255
b100 L
b100 I
b10 M
1K
0<
b10 :
b10 J
b100 !
b100 ?
1D
0B
b111 "
b111 @
10
b0 E
b111 7
b111 Q
b11111111111111111111111111111111 X
b11 W
b10011000 U
b1111 1
b1111 \
b10011 -
b11 ,
b1001 +
b1001 /
b1001 O
b1001 S
b1001 Z
b1000 *
b1000 .
b1000 N
b1000 R
b1000 Y
1$
1a
#260
0$
0a
#265
1<
b100 L
b1010 I
b1 M
1K
b1 :
b1 J
b0 !
b0 ?
0D
b0 "
b0 @
00
b10 F
b10 E
b1001 7
b1001 Q
b100 4
b100 V
b11111111111111111111111111111111 X
b100 W
b1100110 U
b0 1
b0 \
b10100 -
b10 ,
b110 +
b110 /
b110 O
b110 S
b110 Z
b110 *
b110 .
b110 N
b110 R
b110 Y
1$
1a
#270
0$
0a
#275
b100 L
b1000 I
b11 M
1K
0<
b11 :
b11 J
b100 !
b100 ?
1D
b111 "
b111 @
10
b0 E
b111 7
b111 Q
b11111111111111111111111111111111 X
b100 W
b10101100 U
b10 1
b10 \
b10101 -
b11 ,
b1010 +
b1010 /
b1010 O
b1010 S
b1010 Z
b1100 *
b1100 .
b1100 N
b1100 R
b1100 Y
1$
1a
#280
0$
0a
#285
1<
b100 L
b101 I
b0 M
1K
b0 :
b0 J
b10 !
b10 ?
1B
0D
b1110 "
b1110 @
b1 F
b1 E
b1110 7
b1110 Q
b11 4
b11 V
b11111111111111111111111111111111 X
b11 W
b1010001 U
b1100 1
b1100 \
b10110 -
b101 +
b101 /
b101 O
b101 S
b101 Z
b1 *
b1 .
b1 N
b1 R
b1 Y
1$
1a
#290
0$
0a
#295
b100 L
b1011 I
1K
1<
b100 !
b100 ?
1D
0B
b1 "
b1 @
00
b10 F
b11 E
b101 7
b101 Q
b101 4
b101 V
b11111111111111111111111111111111 X
b101 W
b10101011 U
b1 1
b1 \
b10111 -
b10 ,
b1010 +
b1010 /
b1010 O
b1010 S
b1010 Z
b1011 *
b1011 .
b1011 N
b1011 R
b1011 Y
1$
1a
#300
0$
0a
#305
b100 L
b101 I
1K
1<
b10 !
b10 ?
1B
0D
b1110 "
b1110 @
10
b1 F
b1 E
b1110 7
b1110 Q
b11 4
b11 V
b11111111111111111111111111111111 X
b11 W
b10101 U
b100 1
b100 \
b11000 -
b1 ,
b1 +
b1 /
b1 O
b1 S
b1 Z
b101 *
b101 .
b101 N
b101 R
b101 Y
1$
1a
#310
0$
0a
#315
b1 :
b1 J
b1 M
b100 L
b10 I
1K
0<
1B
b1111 "
b1111 @
b0 F
b10 E
b1111 7
b1111 Q
b11111111111111111111111111111111 X
b11 W
b11000010 U
b110 1
b110 \
b11001 -
b11 ,
b1100 +
b1100 /
b1100 O
b1100 S
b1100 Z
b10 *
b10 .
b10 N
b10 R
b10 Y
1$
1a
#320
0$
0a
#325
1<
b100 L
b11 I
b0 M
1K
b0 :
b0 J
b100 !
b100 ?
1D
0B
b111 "
b111 @
b11 E
b111 7
b111 Q
b101 4
b101 V
b11111111111111111111111111111111 X
b101 W
b10001111 U
b111 1
b111 \
b11010 -
b1000 +
b1000 /
b1000 O
b1000 S
b1000 Z
b1111 *
b1111 .
b1111 N
b1111 R
b1111 Y
1$
1a
#330
0$
0a
#335
1D
b11 "
b11 @
b11 7
b11 Q
b110 4
b110 V
b11111111111111111111111111111111 X
b110 W
b11001111 U
b11 1
b11 \
b11011 -
b1100 +
b1100 /
b1100 O
b1100 S
b1100 Z
1$
1a
#340
0$
0a
#345
b100 L
b101 I
1K
1<
b0 !
b0 ?
0D
b0 "
b0 @
00
b1 F
b1 E
b110 7
b110 Q
b100 4
b100 V
b11111111111111111111111111111111 X
b100 W
b10011001 U
b0 1
b0 \
b11100 -
b0 ,
b1001 +
b1001 /
b1001 O
b1001 S
b1001 Z
b1001 *
b1001 .
b1001 N
b1001 R
b1001 Y
1$
1a
#350
0$
0a
#355
b100 L
b111 I
1K
1<
b100 !
b100 ?
1D
b110 "
b110 @
b11 E
b1110 7
b1110 Q
b11111111111111111111111111111111 X
b100 W
b10111 U
b110 1
b110 \
b11101 -
b10 ,
b1 +
b1 /
b1 O
b1 S
b1 Z
b111 *
b111 .
b111 N
b111 R
b111 Y
1$
1a
#360
0$
0a
#365
b11 :
b11 J
b11 M
b100 L
b1000 I
1K
0<
b10 !
b10 ?
1B
0D
b1010 "
b1010 @
b10 F
b0 E
b1111 7
b1111 Q
b11 4
b11 V
b11111111111111111111111111111111 X
b11 W
b101100 U
b1010 1
b1010 \
b11110 -
b0 ,
b10 +
b10 /
b10 O
b10 S
b10 Z
b1100 *
b1100 .
b1100 N
b1100 R
b1100 Y
1$
1a
#370
0$
0a
#375
1<
b100 L
b111 I
b0 M
1K
b0 :
b0 J
b1010 !
b1010 ?
1C
1B
b1010 "
b1010 @
b1 F
b11 E
b1010 7
b1010 Q
b110 4
b110 V
b11111111111111111111111111111111 X
b110 W
b11010111 U
12
b11111 -
b10 ,
b1101 +
b1101 /
b1101 O
b1101 S
b1101 Z
b111 *
b111 .
b111 N
b111 R
b111 Y
1$
1a
#380
0$
0a
#385
b1 :
b1 J
b1 M
b100 L
b110 I
1K
1<
b100 !
b100 ?
1D
0B
0C
b11 "
b11 @
10
b10 E
b11 7
b11 Q
b11111111111111111111111111111111 X
b110 W
b11011110 U
02
b1 1
b1 \
b100000 -
b1 ,
b1110 *
b1110 .
b1110 N
b1110 R
b1110 Y
1$
1a
#390
0$
0a
#395
b100 L
b1111 I
b0 M
1K
1<
b0 :
b0 J
b10 !
b10 ?
1B
0D
b1100 "
b1100 @
b11 F
b11 E
b1100 7
b1100 Q
b11111111111111111111111111111111 X
b110 W
b111111 U
b1100 1
b1100 \
b100001 -
b11 +
b11 /
b11 O
b11 S
b11 Z
b1111 *
b1111 .
b1111 N
b1111 R
b1111 Y
1$
1a
#400
0$
0a
#405
b10 :
b10 J
b10 M
b100 L
b1100 I
1K
1<
b100 !
b100 ?
1D
0B
b111 "
b111 @
b0 E
b111 7
b111 Q
b100 4
b100 V
b11111111111111111111111111111111 X
b100 W
b10111000 U
b1101 1
b1101 \
b100010 -
b1011 +
b1011 /
b1011 O
b1011 S
b1011 Z
b1000 *
b1000 .
b1000 N
b1000 R
b1000 Y
1$
1a
#410
0$
0a
#415
b100 L
b1011 I
b0 M
1K
1<
b0 :
b0 J
1D
b101 "
b101 @
00
b10 F
b11 E
b101 7
b101 Q
b110 4
b110 V
b11111111111111111111111111111111 X
b110 W
b10101111 U
b101 1
b101 \
b100011 -
b0 ,
b1010 +
b1010 /
b1010 O
b1010 S
b1010 Z
b1111 *
b1111 .
b1111 N
b1111 R
b1111 Y
1$
1a
#420
0$
0a
#425
b1 :
b1 J
b1 M
b100 L
b1010 I
1K
1<
b1010 !
b1010 ?
1B
1C
0D
b1000 "
b1000 @
b10 E
b1001 7
b1001 Q
b101 4
b101 V
b11111111111111111111111111111111 X
b101 W
b11100110 U
12
b1000 1
b1000 \
b100100 -
b1110 +
b1110 /
b1110 O
b1110 S
b1110 Z
b110 *
b110 .
b110 N
b110 R
b110 Y
1$
1a
#430
0$
0a
#435
b10 !
b10 ?
1B
0C
b1101 "
b1101 @
10
b1101 7
b1101 Q
b100 4
b100 V
b11111111111111111111111111111111 X
b100 W
b1101010 U
b100 1
b100 \
b100101 -
b11 ,
b110 +
b110 /
b110 O
b110 S
b110 Z
b1010 *
b1010 .
b1010 N
b1010 R
b1010 Y
1$
1a
#440
0$
0a
#445
b100 L
b1111 I
b0 M
1K
1<
b0 :
b0 J
1B
b1100 "
b1100 @
b11 F
b11 E
b1100 7
b1100 Q
b110 4
b110 V
b11111111111111111111111111111111 X
b110 W
b11110011 U
02
b100110 -
b1111 +
b1111 /
b1111 O
b1111 S
b1111 Z
b11 *
b11 .
b11 N
b11 R
b11 Y
1$
1a
#450
0$
0a
